dekmedia-0.1.38.dist-info/METADATA
dekmedia-0.1.38.dist-info/WHEEL
dekmedia-0.1.38.dist-info/entry_points.txt
dekmedia/__init__.py
dekmedia/audio/__init__.py
dekmedia/audio/core/__init__.py
dekmedia/audio/core/res/failure.mp3
dekmedia/audio/core/res/success.mp3
dekmedia/click/__entry__.py
dekmedia/click/__init__.py
dekmedia/click/audio.py
dekmedia/click/font.py
dekmedia/click/image.py
dekmedia/font/__init__.py
dekmedia/font/const/__init__.py
dekmedia/font/manager/__init__.py
dekmedia/font/manager/base/__init__.py
dekmedia/font/manager/default.py
dekmedia/font/path/__init__.py
dekmedia/font/res/afm/cmex10.afm
dekmedia/font/res/afm/cmmi10.afm
dekmedia/font/res/afm/cmr10.afm
dekmedia/font/res/afm/cmsy10.afm
dekmedia/font/res/afm/cmtt10.afm
dekmedia/font/res/afm/pagd8a.afm
dekmedia/font/res/afm/pagdo8a.afm
dekmedia/font/res/afm/pagk8a.afm
dekmedia/font/res/afm/pagko8a.afm
dekmedia/font/res/afm/pbkd8a.afm
dekmedia/font/res/afm/pbkdi8a.afm
dekmedia/font/res/afm/pbkl8a.afm
dekmedia/font/res/afm/pbkli8a.afm
dekmedia/font/res/afm/pcrb8a.afm
dekmedia/font/res/afm/pcrbo8a.afm
dekmedia/font/res/afm/pcrr8a.afm
dekmedia/font/res/afm/pcrro8a.afm
dekmedia/font/res/afm/phvb8a.afm
dekmedia/font/res/afm/phvb8an.afm
dekmedia/font/res/afm/phvbo8a.afm
dekmedia/font/res/afm/phvbo8an.afm
dekmedia/font/res/afm/phvl8a.afm
dekmedia/font/res/afm/phvlo8a.afm
dekmedia/font/res/afm/phvr8a.afm
dekmedia/font/res/afm/phvr8an.afm
dekmedia/font/res/afm/phvro8a.afm
dekmedia/font/res/afm/phvro8an.afm
dekmedia/font/res/afm/pncb8a.afm
dekmedia/font/res/afm/pncbi8a.afm
dekmedia/font/res/afm/pncr8a.afm
dekmedia/font/res/afm/pncri8a.afm
dekmedia/font/res/afm/pplb8a.afm
dekmedia/font/res/afm/pplbi8a.afm
dekmedia/font/res/afm/pplr8a.afm
dekmedia/font/res/afm/pplri8a.afm
dekmedia/font/res/afm/psyr.afm
dekmedia/font/res/afm/ptmb8a.afm
dekmedia/font/res/afm/ptmbi8a.afm
dekmedia/font/res/afm/ptmr8a.afm
dekmedia/font/res/afm/ptmri8a.afm
dekmedia/font/res/afm/putb8a.afm
dekmedia/font/res/afm/putbi8a.afm
dekmedia/font/res/afm/putr8a.afm
dekmedia/font/res/afm/putri8a.afm
dekmedia/font/res/afm/pzcmi8a.afm
dekmedia-0.1.38.dist-info/RECORD
