Metadata-Version: 2.1
Name: dekmedia
Version: 0.1.38
Author-Email: sanzenwin <sanzenwin@gmail.com>
License: MIT
Requires-Python: >=3.7
Requires-Dist: dektools<1.0.0
Provides-Extra: audio
Requires-Dist: just-playback<=0.1.8; extra == "audio"
Provides-Extra: font
Requires-Dist: findsystemfontsfilename<=0.3.1; extra == "font"
Requires-Dist: fonttools<=4.55.2; extra == "font"
Provides-Extra: image
Requires-Dist: pillow<=10.3.0; extra == "image"
Requires-Dist: dekmedia[font]; extra == "image"
Provides-Extra: svg
Requires-Dist: svglib<=1.5.1; extra == "svg"
Requires-Dist: pymupdf<=1.22.5; extra == "svg"
Requires-Dist: svg.path<=6.3; extra == "svg"
Requires-Dist: scour<=0.38.2; extra == "svg"
Requires-Dist: dekmedia[image]; extra == "svg"
Requires-Dist: dektools[yaml]<1.0.0; extra == "svg"
Provides-Extra: psd
Requires-Dist: psd-tools<=1.10.0; extra == "psd"
Requires-Dist: dekmedia[image]; extra == "psd"
Provides-Extra: qr
Requires-Dist: qrcode<=8.0; extra == "qr"
Requires-Dist: dekmedia[image]; extra == "qr"
Provides-Extra: all
Requires-Dist: dekmedia[audio,font,image,psd,qr,svg]; extra == "all"
